genre/__init__.py
genre/config.py
genre/genre.py
genre/secrets.override.yml
genre/secrets.yml
genre/version.py
genre.py-0.2.1.dist-info/DESCRIPTION.rst
genre.py-0.2.1.dist-info/METADATA
genre.py-0.2.1.dist-info/RECORD
genre.py-0.2.1.dist-info/WHEEL
genre.py-0.2.1.dist-info/entry_points.txt
genre.py-0.2.1.dist-info/metadata.json
genre.py-0.2.1.dist-info/top_level.txt
genre.py-0.2.1.dist-info/zip-safe
