Metadata-Version: 2.0
Name: genre.py
Version: 0.2.1
Summary: genre.py looks up the genre of a particular album on discogs and updates ID3 data accordingly.
Home-page: http://github.com/radusuciu/genre.py
Author: Radu Suciu
Author-email: radusuciu@gmail.com
License: Apache Software License
Platform: any
Classifier: Environment :: Console
Classifier: Topic :: Multimedia :: Sound/Audio :: Editors
Classifier: Intended Audience :: End Users/Desktop
Classifier: Programming Language :: Python :: 3
Classifier: Development Status :: 3 - Alpha
Classifier: Natural Language :: English
Classifier: Intended Audience :: Developers
Classifier: License :: OSI Approved :: Apache Software License
Classifier: Operating System :: OS Independent
Classifier: Topic :: Software Development :: Libraries :: Python Modules
Requires-Dist: certifi (==2018.1.18)
Requires-Dist: chardet (==3.0.4)
Requires-Dist: click (==6.7)
Requires-Dist: colorama (==0.3.9)
Requires-Dist: discogs-client (==2.2.1)
Requires-Dist: eyeD3 (==0.8.4)
Requires-Dist: idna (==2.6)
Requires-Dist: oauthlib (==2.0.6)
Requires-Dist: pathlib (==1.0.1)
Requires-Dist: python-magic (==0.4.15)
Requires-Dist: PyYAML (==3.12)
Requires-Dist: requests (==2.18.4)
Requires-Dist: six (==1.11.0)
Requires-Dist: urllib3 (==1.22)
Requires-Dist: python-magic-bin (==0.4.14); sys_platform == "win32" or sys_platform == "darwin"
